Workbook
Name Slicer_Category: #N/A
Name Slicer_Region: #N/A
Name Slicer_Year: #N/A

Sheet Raw Data
A1: OrderID | B1: OrderDate | C1: ShipDate | D1: DeliveryDate | E1: Region | F1: Country | G1: State | H1: City | I1: Category | J1: Sub-Category | K1: Product | L1: Customer Segment | M1: Sales | N1: Discount | O1: Profit | P1: Quantity | Q1: Payment Mode | R1: Order Priority
A2: 10001 | B2: 44197 | C2: 44199 | D2: 44203 | E2: West | F2: India | G2: Karnataka | H2: Bangalore | I2: Office Supplies | J2: Mobile | K2: Dining Table | L2: Home Office | M2: 58593 | N2: 0.15 | O2: 13209 | P2: 21 | Q2: Credit Card | R2: Critical
A3: 10002 | B3: 44198 | C3: 44200 | D3: 44204 | E3: North | F3: India | G3: Telangana | H3: Delhi | I3: Technology | J3: Laptop | K3: Office Chair | L3: Home Office | M3: 71540 | N3: 0.25 | O3: 17196 | P3: 22 | Q3: Credit Card | R3: Medium
A4: 10003 | B4: 44199 | C4: 44201 | D4: 44205 | E4: South | F4: India | G4: Telangana | H4: Kochi | I4: Office Supplies | J4: Printer | K4: Gaming Laptop | L4: Home Office | M4: 65230 | N4: 0.35 | O4: 1181 | P4: 17 | Q4: Net Banking | R4: High
A5: 10004 | B5: 44200 | C5: 44202 | D5: 44206 | E5: East | F5: India | G5: Delhi | H5: Bangalore | I5: Technology | J5: Printer | K5: Office Chair | L5: Consumer | M5: 44292 | N5: 0.25 | O5: 16220 | P5: 13 | Q5: Credit Card | R5: Critical
A6: 10005 | B6: 44201 | C6: 44203 | D6: 44207 | E6: West | F6: India | G6: Kerala | H6: Delhi | I6: Furniture | J6: Notebook | K6: Office Chair | L6: Consumer | M6: 9733 | N6: 0.03 | O6: -225 | P6: 24 | Q6: Credit Card | R6: Critical
A7: 10006 | B7: 44202 | C7: 44204 | D7: 44208 | E7: West | F7: India | G7: Delhi | H7: Chennai | I7: Technology | J7: Notebook | K7: Spiral Notebook | L7: Corporate | M7: 12743 | N7: 0.13 | O7: 19285 | P7: 18 | Q7: UPI | R7: Critical
A8: 10007 | B8: 44203 | C8: 44205 | D8: 44209 | E8: West | F8: India | G8: Tamil Nadu | H8: Mumbai | I8: Office Supplies | J8: Printer | K8: Gel Pen | L8: Corporate | M8: 24441 | N8: 0.15 | O8: 2384 | P8: 5 | Q8: Debit Card | R8: Low
A9: 10008 | B9: 44204 | C9: 44206 | D9: 44210 | E9: West | F9: India | G9: Maharashtra | H9: Bangalore | I9: Technology | J9: Laptop | K9: Spiral Notebook | L9: Corporate | M9: 71119 | N9: 0.28 | O9: 1987 | P9: 23 | Q9: UPI | R9: High
A10: 10009 | B10: 44205 | C10: 44207 | D10: 44211 | E10: North | F10: India | G10: Maharashtra | H10: Mumbai | I10: Technology | J10: Chair | K10: Gel Pen | L10: Consumer | M10: 29497 | N10: 0.15 | O10: 17236 | P10: 10 | Q10: UPI | R10: High
A11: 10010 | B11: 44206 | C11: 44208 | D11: 44212 | E11: South | F11: India | G11: Telangana | H11: Hyderabad | I11: Office Supplies | J11: Chair | K11: Laser Printer | L11: Home Office | M11: 69182 | N11: 0.35 | O11: 3604 | P11: 12 | Q11: Net Banking | R11: Low
A12: 10011 | B12: 44207 | C12: 44209 | D12: 44213 | E12: East | F12: India | G12: Kerala | H12: Mumbai | I12: Technology | J12: Table | K12: Laser Printer | L12: Corporate | M12: 74703 | N12: 0.15 | O12: 12837 | P12: 14 | Q12: Net Banking | R12: Critical
A13: 10012 | B13: 44208 | C13: 44210 | D13: 44214 | E13: West | F13: India | G13: Karnataka | H13: Bangalore | I13: Office Supplies | J13: Printer | K13: Dining Table | L13: Corporate | M13: 60567 | N13: 0.16 | O13: 8255 | P13: 13 | Q13: Cash | R13: High
... A1825: 11824 | B1825: 46020 | C1825: 46022 | D1825: 46026 | E1825: East | F1825: India | G1825: Maharashtra | H1825: Bangalore | I1825: Furniture | J1825: Table | K1825: Gaming Laptop | L1825: Consumer | M1825: 13981 | N1825: 0.36 | O1825: 7969 | P1825: 15 | Q1825: Debit Card | R1825: Low

Sheet Cleaned Data
A1: OrderID | B1: OrderDate | C1: ShipDate | D1: DeliveryDate | E1: Region | F1: Country | G1: State | H1: City | I1: Category | J1: Sub-Category | K1: Product | L1: Customer Segment | M1: Sales | N1: Discount | O1: Profit | P1: Quantity | Q1: Payment Mode | R1: Order Priority | S1: Year | T1: Month | U1: Shipping Days | V1: Delivery Days | W1: Profit%
A2: 10001 | B2: 44197 | C2: 44199 | D2: 44203 | E2: West | F2: India | G2: Karnataka | H2: Bangalore | I2: Office Supplies | J2: Mobile | K2: Dining Table | L2: Home Office | M2: 58593 | N2: 0.15 | O2: 13209 | P2: 21 | Q2: Credit Card | R2: Critical | S2: =YEAR(B2) -> 2021 | T2: =TEXT(B2,"mmm") -> Jan | U2: =C2-B2 -> 2 | V2: =D2-B2 -> 6 | W2: =IFERROR(O2/M2,0) -> 0.22543649
A3: 10002 | B3: 44198 | C3: 44204 | D3: 44208 | E3: North | F3: India | G3: Telangana | H3: Delhi | I3: Technology | J3: Laptop | K3: Office Chair | L3: Home Office | M3: 71540 | N3: 0.25 | O3: 17196 | P3: 22 | Q3: Credit Card | R3: Medium | S3: =YEAR(B3) -> 2021 | T3: =TEXT(B3,"mmm") -> Jan | U3: =C3-B3 -> 6 | V3: =D3-B3 -> 10 | W3: =IFERROR(O3/M3,0) -> 0.24036902
A4: 10003 | B4: 44199 | C4: 44206 | D4: 44208 | E4: South | F4: India | G4: Telangana | H4: Kochi | I4: Office Supplies | J4: Printer | K4: Gaming Laptop | L4: Home Office | M4: 65230 | N4: 0.35 | O4: 1181 | P4: 17 | Q4: Net Banking | R4: High | S4: =YEAR(B4) -> 2021 | T4: =TEXT(B4,"mmm") -> Jan | U4: =C4-B4 -> 7 | V4: =D4-B4 -> 9 | W4: =IFERROR(O4/M4,0) -> 0.018105166
A5: 10004 | B5: 44200 | C5: 44205 | D5: 44208 | E5: East | F5: India | G5: Delhi | H5: Bangalore | I5: Technology | J5: Printer | K5: Office Chair | L5: Consumer | M5: 44292 | N5: 0.25 | O5: 16220 | P5: 13 | Q5: Credit Card | R5: Critical | S5: =YEAR(B5) -> 2021 | T5: =TEXT(B5,"mmm") -> Jan | U5: =C5-B5 -> 5 | V5: =D5-B5 -> 8 | W5: =IFERROR(O5/M5,0) -> 0.36620609
A6: 10005 | B6: 44201 | C6: 44206 | D6: 44207 | E6: West | F6: India | G6: Kerala | H6: Delhi | I6: Furniture | J6: Notebook | K6: Office Chair | L6: Consumer | M6: 9733 | N6: 0.03 | O6: -225 | P6: 24 | Q6: Credit Card | R6: Critical | S6: =YEAR(B6) -> 2021 | T6: =TEXT(B6,"mmm") -> Jan | U6: =C6-B6 -> 5 | V6: =D6-B6 -> 6 | W6: =IFERROR(O6/M6,0) -> -0.02311723
A7: 10006 | B7: 44202 | C7: 44204 | D7: 44208 | E7: West | F7: India | G7: Delhi | H7: Chennai | I7: Technology | J7: Notebook | K7: Spiral Notebook | L7: Corporate | M7: 12743 | N7: 0.13 | O7: 19285 | P7: 18 | Q7: UPI | R7: Critical | S7: =YEAR(B7) -> 2021 | T7: =TEXT(B7,"mmm") -> Jan | U7: =C7-B7 -> 2 | V7: =D7-B7 -> 6 | W7: =IFERROR(O7/M7,0) -> 1.5133799
A8: 10007 | B8: 44203 | C8: 44209 | D8: 44211 | E8: West | F8: India | G8: Tamil Nadu | H8: Mumbai | I8: Office Supplies | J8: Printer | K8: Gel Pen | L8: Corporate | M8: 24441 | N8: 0.15 | O8: 2384 | P8: 5 | Q8: Debit Card | R8: Low | S8: =YEAR(B8) -> 2021 | T8: =TEXT(B8,"mmm") -> Jan | U8: =C8-B8 -> 6 | V8: =D8-B8 -> 8 | W8: =IFERROR(O8/M8,0) -> 0.097541017
A9: 10008 | B9: 44204 | C9: 44207 | D9: 44209 | E9: West | F9: India | G9: Maharashtra | H9: Bangalore | I9: Technology | J9: Laptop | K9: Spiral Notebook | L9: Corporate | M9: 71119 | N9: 0.28 | O9: 1987 | P9: 23 | Q9: UPI | R9: High | S9: =YEAR(B9) -> 2021 | T9: =TEXT(B9,"mmm") -> Jan | U9: =C9-B9 -> 3 | V9: =D9-B9 -> 5 | W9: =IFERROR(O9/M9,0) -> 0.027939088
A10: 10009 | B10: 44205 | C10: 44207 | D10: 44208 | E10: North | F10: India | G10: Maharashtra | H10: Mumbai | I10: Technology | J10: Chair | K10: Gel Pen | L10: Consumer | M10: 29497 | N10: 0.15 | O10: 17236 | P10: 10 | Q10: UPI | R10: High | S10: =YEAR(B10) -> 2021 | T10: =TEXT(B10,"mmm") -> Jan | U10: =C10-B10 -> 2 | V10: =D10-B10 -> 3 | W10: =IFERROR(O10/M10,0) -> 0.58433061
A11: 10010 | B11: 44206 | C11: 44213 | D11: 44215 | E11: South | F11: India | G11: Telangana | H11: Hyderabad | I11: Office Supplies | J11: Chair | K11: Laser Printer | L11: Home Office | M11: 69182 | N11: 0.35 | O11: 3604 | P11: 12 | Q11: Net Banking | R11: Low | S11: =YEAR(B11) -> 2021 | T11: =TEXT(B11,"mmm") -> Jan | U11: =C11-B11 -> 7 | V11: =D11-B11 -> 9 | W11: =IFERROR(O11/M11,0) -> 0.052094475
A12: 10011 | B12: 44207 | C12: 44214 | D12: 44215 | E12: East | F12: India | G12: Kerala | H12: Mumbai | I12: Technology | J12: Table | K12: Laser Printer | L12: Corporate | M12: 74703 | N12: 0.15 | O12: 12837 | P12: 14 | Q12: Net Banking | R12: Critical | S12: =YEAR(B12) -> 2021 | T12: =TEXT(B12,"mmm") -> Jan | U12: =C12-B12 -> 7 | V12: =D12-B12 -> 8 | W12: =IFERROR(O12/M12,0) -> 0.17184049
A13: 10012 | B13: 44208 | C13: 44211 | D13: 44212 | E13: West | F13: India | G13: Karnataka | H13: Bangalore | I13: Office Supplies | J13: Printer | K13: Dining Table | L13: Corporate | M13: 60567 | N13: 0.16 | O13: 8255 | P13: 13 | Q13: Cash | R13: High | S13: =YEAR(B13) -> 2021 | T13: =TEXT(B13,"mmm") -> Jan | U13: =C13-B13 -> 3 | V13: =D13-B13 -> 4 | W13: =IFERROR(O13/M13,0) -> 0.13629534
... A1822: 11821 | B1822: 46017 | C1822: 46021 | D1822: 46025 | E1822: North | F1822: India | G1822: Maharashtra | H1822: Mumbai | I1822: Office Supplies | J1822: Notebook | K1822: Gel Pen | L1822: Home Office | M1822: 12451 | N1822: 0.39 | O1822: 9244 | P1822: 11 | Q1822: Cash | R1822: High | S1822: =YEAR(B1822) -> 2025 | T1822: =TEXT(B1822,"mmm") -> Dec | U1822: =C1822-B1822 -> 4 | V1822: =D1822-B1822 -> 8 | W1822: =IFERROR(O1822/M1822,0) -> 0.74243033

Sheet Pivot _analysis
A1: Row Labels | B1: Sum of Sales | C1: Sum of Profit | D1: Sum of Profit Margin
A2: East | B2: 16352629 | C2: 3723311 | D2: 0.22768883
A3: North | B3: 17972987 | C3: 4282940 | D3: 0.23829873
A4: South | B4: 16209153 | C4: 4215736 | D4: 0.26008367
A5: West | B5: 17499731 | C5: 3685325 | D5: 0.21059324
A6: Grand Total | B6: 68034500 | C6: 15907312 | D6: 0.23381243
A20: Row Labels | B20: Sum of Sales
A21: Jan | B21: 5779130
A22: Feb | B22: 5075046
A23: Mar | B23: 5932464
A24: Apr | B24: 5065205
A25: May | B25: 5959189
A26: Jun | B26: 5929863
A27: Jul | B27: 5579491
A28: Aug | B28: 5875782
A29: Sep | B29: 5509149
A30: Oct | B30: 6040865
A31: Nov | B31: 5749556
A32: Dec | B32: 5538760
A33: Grand Total | B33: 68034500
A38: Row Labels | B38: Sum of Sales | C38: Sum of Profit
A39: Furniture | B39: 22869774 | C39: 5391261
A40: Office Supplies | B40: 22246691 | C40: 5205281
A41: Technology | B41: 22918035 | C41: 5310770
A42: Grand Total | B42: 68034500 | C42: 15907312
A53: Sum of Sales | B53: Sum of Profit | C53: Sum of Profit Margin | D53: Sum of OrderID | E53: Sum of Delivery Days
A54: 68034500 | B54: 15907312 | C54: 0.23381243 | D54: 19868931 | E54: 13630

Sheet KPI Summary
A1: KPI SUMMARY
A3: Total Sales | B3: =GETPIVOTDATA("Sum of Sales",'Pivot _analysis'!$A$53) -> 68034500
A4: Total Profit | B4: =GETPIVOTDATA("Sum of Profit",'Pivot _analysis'!$A$53) -> 15907312
A5: Profit Margin% | B5: =GETPIVOTDATA("Sum of Profit Margin",'Pivot _analysis'!$A$53) -> 0.23381243
A6: Total Orders | B6: =GETPIVOTDATA("Sum of OrderID",'Pivot _analysis'!$A$53) -> 19868931
A7: Avg Delivery Days | B7: =GETPIVOTDATA("Sum of Delivery Days",'Pivot _analysis'!$A$53) -> 13630

Sheet Dashboard
